Workbook
Name aporte: Planilha1!$D$22
Name patrimonio: Planilha1!$D$25
Name qtd_anos: Planilha1!$D$23
Name rendimento_carteira: Planilha1!$D$18
Name salario: Planilha1!$D$17
Name sugestao: Planilha1!$D$19
Name taxa_mensal: Planilha1!$D$24

Sheet Planilha1
B16: CONFIGURAÇÕES
B17: Salário | D17: 5000
B18: Rendimento de salário | D18: 0.6
B19: Sugestao de investimento | D19: =$D$17*(0.3) -> 1500
B21: INVESTIMENTO MENSAL
B22: Aporte | D22: 250
B23: Por quantos anos ? | D23: 5
B24: Taxa de rendimento mensal | D24: 0.01079
B25: Patrimônio acumulado | D25: =FV(taxa_mensal,qtd_anos*12,aporte*(-1)) -> 20944.228
B26: Dividendo mensais | D26: =patrimonio*rendimento_carteira -> 12566.537
B28: Cenários | D28: Dividendo
A29: 2 | B29: Quanto em 2 anos ? | C29: =FV($D$24, A29*12,$D$22*(-1)) -> 6806.9068 | D29: =C29*rendimento_carteira -> 4084.1441
A30: 5 | B30: Quanto em 5 anos ? | C30: =FV($D$24, A30*12,$D$22*(-1)) -> 20944.228 | D30: =C30*rendimento_carteira -> 12566.537
A31: 10 | B31: Quanto em 10 anos ? | C31: =FV($D$24, A31*12,$D$22*(-1)) -> 60821.053 | D31: =C31*rendimento_carteira -> 36492.632
A32: 20 | B32: Quantos em 20 anos ? | C32: =FV($D$24, A32*12,$D$22*(-1)) -> 281299.6 | D32: =C32*rendimento_carteira -> 168779.76
A33: 30 | B33: Quanto em 30 anos ? | C33: =FV($D$24, A33*12,$D$22*(-1)) -> 1080542.4 | D33: =C33*rendimento_carteira -> 648325.45
B35: Perfil | C35: CONSERVADOR
B36: VALOR A SER INVESTIDO | C36: =aporte -> 250
B38: TIPO DE FII | C38: PERCENTUAL SUGERIDO | D38: VALORES
B39: TIJOLO | C39: =VLOOKUP($C$35&"-"&B39,Planilha2!$A:$D,4,FALSE) -> 0.5 | D39: =C39*$C$36 -> 125
B40: PAPEL | C40: =VLOOKUP($C$35&"-"&B40,Planilha2!$A:$D,4,FALSE) -> 0.1 | D40: =C40*$C$36 -> 25
B41: HIBRIDOS | C41: =VLOOKUP($C$35&"-"&B41,Planilha2!$A:$D,4,FALSE) -> 0.05 | D41: =C41*$C$36 -> 12.5
B42: FOF's | C42: =VLOOKUP($C$35&"-"&B42,Planilha2!$A:$D,4,FALSE) -> 0.05 | D42: =C42*$C$36 -> 12.5
B43: DESENVOLVIMENTO | C43: =VLOOKUP($C$35&"-"&B43,Planilha2!$A:$D,4,FALSE) -> 0.2 | D43: =C43*$C$36 -> 50
B44: HOTELARIAS | C44: =VLOOKUP($C$35&"-"&B44,Planilha2!$A:$D,4,FALSE) -> 0.1 | D44: =C44*$C$36 -> 25
C45: TOTAL: | D45: =SUM(D39:D44) -> 250

Sheet Planilha2
A2: CHAVE | B2: Perfil | C2: Tipo | D2: %
A3: =B3&"-"&C3 -> AGRESSIVO-TIJOLO | B3: AGRESSIVO | C3: TIJOLO | D3: 0.3
A4: =B4&"-"&C4 -> AGRESSIVO-PAPEL | B4: AGRESSIVO | C4: PAPEL | D4: 0.5
A5: =B5&"-"&C5 -> AGRESSIVO-HIBRIDOS | B5: AGRESSIVO | C5: HIBRIDOS | D5: 0.1
A6: =B6&"-"&C6 -> AGRESSIVO-FOF's | B6: AGRESSIVO | C6: FOF's | D6: 0.1 | F6: AGRESSIVO-TIJOLO | G6: =VLOOKUP(Planilha1!C39,$A:$D,4,FALSE) -> #N/A
A7: =B7&"-"&C7 -> AGRESSIVO-DESENVOLVIMENTO | B7: AGRESSIVO | C7: DESENVOLVIMENTO | D7: 0
A8: =B8&"-"&C8 -> AGRESSIVO-HOTELARIAS | B8: AGRESSIVO | C8: HOTELARIAS | D8: 0
A9: =B9&"-"&C9 -> MODERADO-TIJOLO | B9: MODERADO | C9: TIJOLO | D9: 0.32
A10: =B10&"-"&C10 -> MODERADO-PAPEL | B10: MODERADO | C10: PAPEL | D10: 0.35
A11: =B11&"-"&C11 -> MODERADO-HIBRIDOS | B11: MODERADO | C11: HIBRIDOS | D11: 0.08
A12: =B12&"-"&C12 -> MODERADO-FOF's | B12: MODERADO | C12: FOF's | D12: 0.05
A13: =B13&"-"&C13 -> MODERADO-DESENVOLVIMENTO | B13: MODERADO | C13: DESENVOLVIMENTO | D13: 0.1
A14: =B14&"-"&C14 -> MODERADO-HOTELARIAS | B14: MODERADO | C14: HOTELARIAS | D14: 0.1
A15: =B15&"-"&C15 -> CONSERVADOR-TIJOLO | B15: CONSERVADOR | C15: TIJOLO | D15: 0.5
A16: =B16&"-"&C16 -> CONSERVADOR-PAPEL | B16: CONSERVADOR | C16: PAPEL | D16: 0.1
A17: =B17&"-"&C17 -> CONSERVADOR-HIBRIDOS | B17: CONSERVADOR | C17: HIBRIDOS | D17: 0.05
A18: =B18&"-"&C18 -> CONSERVADOR-FOF's | B18: CONSERVADOR | C18: FOF's | D18: 0.05
... A20: =B20&"-"&C20 -> CONSERVADOR-HOTELARIAS | B20: CONSERVADOR | C20: HOTELARIAS | D20: 0.1
